<?xml version="1.0"?>
<map proto="1.4.2">
<name>Waterwood</name>
<version>1.0.1</version>
<created>2021-12-14</created>
<objective>Destroy 100% of the opposing team's emerald monument to win!</objective>
<authors>
    <author uuid="86b8ea93-6936-4b28-9d0c-19004d0dcb51"/> <!-- Wyviryn -->
</authors>
<contributors>
    <contributor uuid="5c79d2c9-a4f0-4343-a84b-e1720f13009b" contribution="XML assistance"/> <!-- CoWinkKeyDinkInc -->
    <contributor uuid="e2d2c2c6-cea9-4510-9ab2-a091b5605b30" contribution="More XML help"/> <!-- Ruediger_LP -->
    <contributor uuid="a9f11454-beac-4cc3-a138-1780802c8794" contribution="More XML help"/> <!-- Crazy_ -->
    <contributor uuid="ec5ec930-5cf3-4f8a-ad9f-09056aeed71b" contribution="Construction feedback"/> <!-- Tundren -->
    <contributor uuid="621b2aa8-4e5f-4ed8-bd36-0ae2f8952a06" contribution="Construction feedback"/> <!-- Strangey -->
    <contributor uuid="fe3608b7-d105-4029-8800-34b3147065b6" contribution="Construction feedback"/> <!-- rockymine -->
    <contributor uuid="6863869b-4b8c-4445-b778-a8e016775ae4" contribution="Placed two signs I ended up replacing anyway"/> <!-- Cazadorian -->
</contributors>
<teams>
    <team id="purple-team" color="dark_purple" max="16">Purple</team>
    <team id="green-team" color="green" max="16">Green</team>
</teams>
<kits>
    <kit id="spawn-kit">
        <clear/>
        <item slot="0" material="iron sword" unbreakable="true"/>
        <item slot="1" material="bow" unbreakable="true" enchantment="arrow infinite"/>
        <item slot="2" material="iron pickaxe" unbreakable="true">
            <enchantment level="1">efficiency</enchantment>
        </item>
        <item slot="3" material="iron axe" unbreakable="true">
            <enchantment level="1">efficiency</enchantment>
        </item>
        <item slot="4" material="wood" amount="64" damage="1"/>
        <item slot="6" material="ladder" amount="32"/>
        <item slot="8" material="golden apple"/>
        <item slot="28" material="arrow"/>
        <item slot="30" material="iron spade" unbreakable="true">
            <enchantment level="1">efficiency</enchantment>
        </item>
        <item slot="31" material="wood" amount="64" damage="1"/>
        <chestplate material="leather chestplate" team-color="true" unbreakable="true"/>
        <leggings material="chainmail leggings" unbreakable="true"/>
        <boots material="leather boots" team-color="true" unbreakable="true"/>
        <effect duration="3" amplifier="100">damage resistance</effect>
    </kit>
    <kit id="purple-kit" parent="spawn-kit">
        <item slot="5" material="stained clay" damage="10" amount="32"/>
    </kit>
    <kit id="green-kit" parent="spawn-kit">
        <item slot="5" material="stained clay" damage="5" amount="32"/>
    </kit>
</kits>
<spawns>
    <spawn team="purple-team" kit="purple-kit">
        <regions yaw="-90">
            <point>-26.5,20,63.5</point>
        </regions>
    </spawn>
    <spawn team="green-team" kit="green-kit">
        <regions yaw="90">
            <point>26.5,20,-63.5</point>
        </regions>
    </spawn>
    <default>
        <regions yaw="-90">
            <point>56,49,0</point>
        </regions>
    </default>
</spawns>
<filters>
    <not id="no-void">
        <void/>
    </not>
</filters>
<regions>
    <apply block="never" region="spawns" message="You cannot modify the team spawn areas!"/>
    <apply enter="only-purple-team" region="purple-team-spawn" message="You cannot enter the opposing team's spawn area!"/>
    <apply enter="only-green-team" region="green-team-spawn" message="You cannot enter the opposing team's spawn area!"/>
    <apply block="no-void" message="You can only bridge in the designated side lanes!">
        <region>
            <rectangle id="main-area" min="-100,-100" max="100,100"/>
        </region>
    </apply>
    <union id="spawns">
        <cuboid id="purple-team-spawn" min="-22,13,59" max="-31,28,68"/>
        <cuboid id="green-team-spawn" min="22,13,-59" max="31,28,-68"/>
    </union>
</regions>
<filters>
    <team id="only-purple-team">purple-team</team>
    <team id="only-green-team">green-team</team>
</filters>
<destroyables completion="100%" materials="emerald block">
    <destroyable name="Emerald Monument" owner="purple-team">
        <region> <!-- Purple Monument -->
            <cuboid min="14,15,37" max="10,23,41"/>
        </region>
    </destroyable>
    <destroyable name="Emerald Monument" owner="green-team">
        <region> <!-- Green Monument -->
            <cuboid min="-14,15,-37" max="-10,23,-41"/>
        </region>
    </destroyable>
</destroyables>
<itemkeep>
    <item>iron sword</item>
    <item>bow</item>
    <item>iron pickaxe</item>
    <item>iron axe</item>
    <item>arrow</item>
    <item>iron spade</item>
    <item>wood</item>
    <item>stained clay</item>
    <item>ladder</item>
    <item>golden apple</item>
</itemkeep>
<itemremove>
    <item>leather chestplate</item>
    <item>chainmail leggings</item>
    <item>leather boots</item>
    <item>emerald block</item>
    <item>step</item>
    <item>trap door</item>
    <item>glowstone dust</item>
</itemremove>
<toolrepair>
    <tool>iron sword</tool>
    <tool>bow</tool>
    <tool>iron pickaxe</tool>
    <tool>iron axe</tool>
    <tool>iron spade</tool>
    <tool>arrow</tool>
</toolrepair>
<world>
    <timeset>21213</timeset>
    <timelock>off</timelock>
</world>
<kill-reward>
    <item material="golden apple"/>
    <item amount="32" material="wood" damage="1"/>
</kill-reward>
<hunger>
    <depletion>off</depletion>
</hunger>
<maxbuildheight>31</maxbuildheight>
</map>
