<?xml version="1.0"?>
<map proto="1.4.0">
<name>Hillside Daydream</name>
<version>1.0.1</version>
<objective>Capture each wool from the enemy teams!</objective>
<gamemode>ctw</gamemode>
<created>2022-02-19</created>
<authors>
    <author uuid="d5a64b26-15ea-46c4-8319-f9c83e82a1fa"/> <!-- Eliminate -->
</authors>
<contributors>
    <contributor uuid="ec5ec930-5cf3-4f8a-ad9f-09056aeed71b" contribution="xml"/> <!-- Tundren -->
    <contributor uuid="e2d2c2c6-cea9-4510-9ab2-a091b5605b30" contribution="xml help"/> <!-- Ruediger_LP -->
</contributors>
<teams>
    <team id="blue-team" color="blue" max="16">Blue</team>
    <team id="red-team" color="dark red" max="16">Red</team>
    <team id="green-team" color="green" max="16">Green</team>
    <team id="yellow-team" color="yellow" max="16">Yellow</team>
</teams>
<kits>
    <kit id="spawn-kit">
        <clear/>
        <item slot="0" material="iron sword" unbreakable="true"/>
        <item slot="1" material="bow" unbreakable="true">
            <enchantment>arrow infinite</enchantment>
        </item>
        <item slot="2" material="diamond pickaxe" unbreakable="true"/>
        <item slot="3" material="diamond axe" unbreakable="true"/>
        <item slot="4" material="wood" damage="1" amount="64"/>
        <item slot="5" material="vine" amount="48"/>
        <item slot="8" material="golden apple"/>
        <item slot="28" material="arrow"/>
        <item slot="29" material="shears" unbreakable="true"/>
        <item slot="30" material="iron spade" unbreakable="true"/>
        <helmet material="leather helmet" team-color="true" unbreakable="true"/>
        <chestplate material="leather chestplate" team-color="true" unbreakable="true"/>
        <leggings material="chainmail leggings" unbreakable="true"/>
        <boots material="leather boots" team-color="true" unbreakable="true"/>
        <effect duration="oo" amplifier="100">damage resistance</effect>
    </kit>
    <kit force="true" id="reset-resistance-kit">
        <effect duration="0" amplifier="0">damage resistance</effect>
    </kit>
</kits>
<spawns>
    <spawn team="blue-team" kit="spawn-kit" yaw="-90" region="blue-spawn-point"/>
    <spawn team="red-team" kit="spawn-kit" yaw="180" region="red-spawn-point"/>
    <spawn team="green-team" kit="spawn-kit" yaw="90" region="green-spawn-point"/>
    <spawn team="yellow-team" kit="spawn-kit" yaw="0" region="yellow-spawn-point"/>
    <default yaw="135.7" region="obs-spawn-point"/>
</spawns>
<wools craftable="false">
    <wool team="blue-team" color="red" monument="blue-team-red-wool" location="-96.5,15.2,58.5"/>
    <wool team="blue-team" color="lime" monument="blue-team-green-wool" location="58.5,15.2,96.5"/>
    <wool team="blue-team" color="yellow" monument="blue-team-yellow-wool" location="96.5,15.2,-58.5"/>
    <wool team="red-team" color="lime" monument="red-team-green-wool" location="58.5,15.2,96.5"/>
    <wool team="red-team" color="yellow" monument="red-team-yellow-wool" location="96.5,15.2,-58.5"/>
    <wool team="red-team" color="blue" monument="red-team-blue-wool" location="-58.5,15.2,-96.5"/>
    <wool team="green-team" color="yellow" monument="green-team-yellow-wool" location="96.5,15.2,-58.5"/>
    <wool team="green-team" color="blue" monument="green-team-blue-wool" location="-58.5,15.2,-96.5"/>
    <wool team="green-team" color="red" monument="green-team-red-wool" location="-96.5,15.2,58.5"/>
    <wool team="yellow-team" color="blue" monument="yellow-team-blue-wool" location="-58.5,15.2,-96.5"/>
    <wool team="yellow-team" color="red" monument="yellow-team-red-wool" location="-96.5,15.2,58.5"/>
    <wool team="yellow-team" color="lime" monument="yellow-team-green-wool" location="58.5,15.2,96.5"/>
</wools>
<filters>
    <any id="block-break-void-filter">
        <all>
            <any>
                <material>log</material>
                <material>leaves</material>
                <material>wool:7</material>
                <material>stained clay;9</material>
                <material>prismarine:2</material>
                <material>wood step:1</material>
            </any>
            <void/>
        </all>
        <not id="block-place-void-filter">
            <void/>
        </not>
    </any>
    <all id="blue-woolroom-filter">
        <not id="not-blue">
            <team id="only-blue">blue-team</team>
        </not>
        <filter id="woolroom-filter"/>
        <filter id="block-place-void-filter"/>
    </all>
    <all id="red-woolroom-filter">
        <not id="not-red">
            <team id="only-red">red-team</team>
        </not>
        <filter id="woolroom-filter"/>
        <filter id="block-place-void-filter"/>
    </all>
    <all id="green-woolroom-filter">
        <not id="not-green">
            <team id="only-green">green-team</team>
        </not>
        <filter id="woolroom-filter"/>
        <filter id="block-place-void-filter"/>
    </all>
    <all id="yellow-woolroom-filter">
        <not id="not-yellow">
            <team id="only-yellow">yellow-team</team>
        </not>
        <filter id="woolroom-filter"/>
        <filter id="block-place-void-filter"/>
    </all>
    <any id="woolroom-filter">
        <material>web</material>
        <material>wood:1</material>
        <material>vine</material>
        <all>
            <cause>player</cause>
            <any>
                <material>stationary water</material>
                <material>water</material>
            </any>
        </all>
    </any>
    <all id="only-iron-cause-world">
        <material id="only-iron">iron block</material>
        <cause>world</cause>
    </all>
    <material id="only-air">air</material>
    <deny id="deny-wool">
        <any>
            <material>wool:11</material>
            <material>wool:14</material>
            <material>wool:5</material>
            <material>wool:4</material>
        </any>
    </deny>
</filters>
<regions>
    <cylinder id="blue-spawn-point" base="-99.5,15.2,-34.5" radius="1.5" height="0"/>
    <cylinder id="red-spawn-point" base="-34.5,15.2,99.5" radius="1.5" height="0"/>
    <cylinder id="green-spawn-point" base="99.5,15.2,34.5" radius="1.5" height="0"/>
    <cylinder id="yellow-spawn-point" base="34.5,15.2,-99.5" radius="1.5" height="0"/>
    <cylinder id="obs-spawn-point" base="0,56.2,0" radius="2" height="0"/>
    <block id="blue-team-red-wool">-106,17,-33</block>
    <block id="blue-team-green-wool">-106,17,-35</block>
    <block id="blue-team-yellow-wool">-106,17,-37</block>
    <block id="red-team-green-wool">-33,17,105</block>
    <block id="red-team-yellow-wool">-35,17,105</block>
    <block id="red-team-blue-wool">-37,17,105</block>
    <block id="green-team-yellow-wool">105,17,32</block>
    <block id="green-team-blue-wool">105,17,34</block>
    <block id="green-team-red-wool">105,17,36</block>
    <block id="yellow-team-blue-wool">32,17,-106</block>
    <block id="yellow-team-red-wool">34,17,-106</block>
    <block id="yellow-team-green-wool">36,17,-106</block>
    <point id="blue-wool-spawn">-58.5,15.2,-96.5</point>
    <point id="red-wool-spawn">-96.5,15.2,58.5</point>
    <point id="green-wool-spawn">58.5,15.2,96.5</point>
    <point id="yellow-wool-spawn">96.5,15.2,-58.5</point>
    <negative id="not-spawns">
        <union id="spawns">
            <rectangle id="blue-spawn" min="-111,-47" max="-88,-22"/>
            <rectangle id="red-spawn" min="-47,111" max="-22,88"/>
            <rectangle id="green-spawn" min="111,47" max="88,22"/>
            <rectangle id="yellow-spawn" min="47,-111" max="22,-88"/>
        </union>
    </negative>
    <union id="woolrooms">
        <union id="blue-woolroom">
            <rectangle min="-72,-106" max="-45,-85"/>
            <rectangle id="blue-woolroom-enter" min="-65,-91" max="-52,-85"/>
        </union>
        <union id="red-woolroom">
            <rectangle min="-106,72" max="-85,45"/>
            <rectangle id="red-woolroom-enter" min="-91,65" max="-85,52"/>
        </union>
        <union id="green-woolroom">
            <rectangle min="72,106" max="45,85"/>
            <rectangle id="green-woolroom-enter" min="65,91" max="52,85"/>
        </union>
        <union id="yellow-woolroom">
            <rectangle min="106,-72" max="85,-45"/>
            <rectangle id="yellow-woolroom-enter" min="91,-65" max="85,-52"/>
        </union>
    </union>
    <negative id="not-build-area">
        <union id="build-area">
            <rectangle min="-53,-53" max="53,53"/> <!-- mid -->
        </union>
    </negative>
    <cuboid id="spawner-protection" min="-1,10,-1" max="1,14,1"/>
    <point id="golden-apple-spawn">0,11,0</point> 
    <sphere id="golden-apple-player" origin="0,11,0" radius="6"/>
    <!-- applicators -->
    <apply enter="only-blue" region="blue-spawn" message="You may not enter the enemy's spawn!"/>
    <apply enter="only-red" region="red-spawn" message="You may not enter the enemy's spawn!"/>
    <apply enter="only-green" region="green-spawn" message="You may not enter the enemy's spawn!"/>
    <apply enter="only-yellow" region="yellow-spawn" message="You may not enter the enemy's spawn!"/>
    <apply enter="not-blue" region="blue-woolroom-enter" message="You may not enter your own wool room!"/>
    <apply enter="not-red" region="red-woolroom-enter" message="You may not enter your own wool room!"/>
    <apply enter="not-green" region="green-woolroom-enter" message="You may not enter your own wool room!"/>
    <apply enter="not-yellow" region="yellow-woolroom-enter" message="You may not enter your own wool room!"/>
    <apply block="blue-woolroom-filter" region="blue-woolroom" message="You may not edit the wool room!"/>
    <apply block="red-woolroom-filter" region="red-woolroom" message="You may not edit the wool room!"/>
    <apply block="green-woolroom-filter" region="green-woolroom" message="You may not edit the wool room!"/>
    <apply block="yellow-woolroom-filter" region="yellow-woolroom" message="You may not edit the wool room!"/>
    <apply block-place="only-iron-cause-world" block-break="only-iron" region="spawns" message="You may not edit spawn!"/>
    <apply block="never" region="spawner-protection" message="You may not edit the spawner!"/>
    <apply block-place="block-place-void-filter" block-break="block-break-void-filter" region="not-build-area" message="You may not edit the void!"/>
    <apply block-place="deny-wool" region="everywhere" message="You may only place wool at the victory monument!"/>
    <apply kit="reset-resistance-kit" region="not-spawns"/>
    <apply block-physics="never" region="woolrooms"/>
</regions>
<spawners>
    <spawner spawn-region="blue-wool-spawn" player-region="blue-woolroom" delay="3s">
        <item material="wool" amount="1" damage="11"/>
    </spawner>
    <spawner spawn-region="red-wool-spawn" player-region="red-woolroom" delay="3s">
        <item material="wool" amount="1" damage="14"/>
    </spawner>
    <spawner spawn-region="green-wool-spawn" player-region="green-woolroom" delay="3s">
        <item material="wool" amount="1" damage="5"/>
    </spawner>
    <spawner spawn-region="yellow-wool-spawn" player-region="yellow-woolroom" delay="3s">
        <item material="wool" amount="1" damage="4"/>
    </spawner>
    <spawner spawn-region="golden-apple-spawn" player-region="golden-apple-player" delay="20s">
        <item material="golden apple" amount="1"/>
    </spawner>
</spawners>
<itemkeep>
    <item>iron sword</item>
    <item>bow</item>
    <item>diamond pickaxe</item>
    <item>diamond axe</item>
    <item>iron spade</item>
    <item>shears</item>
    <item>arrow</item>
    <item>wood</item>
    <item>vine</item>
    <item>golden apple</item>
</itemkeep>
<itemremove>
    <item>leather helmet</item>
    <item>leather chestplate</item>
    <item>chainmail leggings</item>
    <item>leather boots</item>
</itemremove>
<toolrepair>
    <tool>iron sword</tool>
    <tool>bow</tool>
    <tool>diamond pickaxe</tool>
    <tool>diamond axe</tool>
    <tool>iron spade</tool>
    <tool>arrow</tool>
</toolrepair>
<item-mods>
    <rule>
        <match>
            <material>iron helmet</material>
            <material>iron chestplate</material>
            <material>iron leggings</material>
            <material>iron boots</material>
            <material>iron sword</material>
            <material>iron pickaxe</material>
            <material>iron axe</material>
            <material>iron spade</material>
            <material>shears</material>
            <material>bow</material>
            <material>diamond chestplate</material>
        </match>
        <modify unbreakable="true"/>
    </rule>
</item-mods>
<crafting>
    <!-- bulkcrafting -->
    <shaped override="false">
        <result material="iron helmet" amount="9"/>
        <shape>
            <row>III</row>
            <row>I.I</row>
        </shape>
        <ingredient symbol="I">iron block</ingredient>
    </shaped>
    <shaped override="false">
        <result material="iron chestplate" amount="9"/>
        <shape>
            <row>I.I</row>
            <row>III</row>
            <row>III</row>
        </shape>
        <ingredient symbol="I">iron block</ingredient>
    </shaped>
    <shaped override="false">
        <result material="iron leggings" amount="9"/>
        <shape>
            <row>III</row>
            <row>I.I</row>
            <row>I.I</row>
        </shape>
        <ingredient symbol="I">iron block</ingredient>
    </shaped>
    <shaped override="false">
        <result material="iron boots" amount="9"/>
        <shape>
            <row>I.I</row>
            <row>I.I</row>
        </shape>
        <ingredient symbol="I">iron block</ingredient>
    </shaped>
    <shaped override="false">
        <result material="bucket" amount="9"/>
        <shape>
            <row>I.I</row>
            <row>.I.</row>
        </shape>
        <ingredient symbol="I">iron block</ingredient>
    </shaped>
</crafting>
<renewables>
    <renewable rate="3" sound="false" region="spawns" renew-filter="only-iron" replace-filter="only-air" avoid-players="2"/>
</renewables>
<rules>
    <rule>Creating alliances with other teams is allowed.</rule>
</rules>
<hunger>
    <depletion>off</depletion>
</hunger>
<timelock>on</timelock>
<maxbuildheight>25</maxbuildheight>
<kill-rewards>
    <kill-reward>
    <item material="golden apple"/>
    <item material="wood" amount="24" damage="1"/>
    </kill-reward>
</kill-rewards>
</map>
